tfdbnet
