Metadata-Version: 2.1
Name: tfdbnet
Version: 0.0.3
Summary: A TensorFlow 2 wrapper of DBNet
Home-page: https://github.com/18520339/dbnet-tf2
Author: Quan Dang
Author-email: 18520339@gm.uit.edu.vn
License: UNKNOWN
Platform: UNKNOWN
Classifier: Programming Language :: Python :: 3
Classifier: License :: OSI Approved :: MIT License
Classifier: Operating System :: OS Independent
License-File: LICENSE
